MANIFEST.in
README.md
setup.py
artice.egg-info/PKG-INFO
artice.egg-info/SOURCES.txt
artice.egg-info/dependency_links.txt
artice.egg-info/requires.txt
artice.egg-info/top_level.txt
finart/__init__.py
finart/url_builder/__init__.py
finart/url_builder/builder.py
finart/url_builder/enums.py
finart/yfinance_data/__init__.py
finart/yfinance_data/config.py
finart/yfinance_data/utils.py
finart/yfinance_data/crawler/__init__.py
finart/yfinance_data/crawler/article_crawler.py
finart/yfinance_data/crawler/sitemap_crawler.py
finart/yfinance_data/crawler/utils.py
finart/yfinance_data/db/__init__.py
finart/yfinance_data/db/mongodb.py
finart/yfinance_data/reader/__init__.py
finart/yfinance_data/reader/sitemap.py
finice/__init__.py
finice/utils.py
finice/tardis_data/__init__.py
finice/tardis_data/config.py
finice/tardis_data/kline.py
finice/tardis_data/raw.py
finice/tardis_data/utils.py
finice/yfinance_data/__init__.py
finice/yfinance_data/config.py
finice/yfinance_data/download.py
finice/yfinance_data/reader.py
finice/yfinance_data/db/__init__.py
finice/yfinance_data/db/mongodb.py
finmod/__init__.py
finmod/loss.py
finmod/train.py
finmod/dataset/__init__.py
finmod/dataset/dataset.py
finmod/dataset/dataset_maker.py
finmod/models/__init__.py
finmod/models/lstm.py
test/__init__.py
test/finart/__init__.py
test/finart/urlbuilder/__init__.py
test/finart/urlbuilder/test_builder.py
utils/__init__.py
utils/date_utils.py
utils/db_utils.py
utils/io_utils.py
utils/log_utils.py
utils/selenium_utils.py