Metadata-Version: 2.1
Name: artice
Version: 0.0.1
Summary: Twisting the magic of financial prices and articles
Author: Steve Flyer
Author-email: steveflyer7@gmail.com
License: MIT
Requires-Dist: lxml
Requires-Dist: tqdm
Requires-Dist: numpy
Requires-Dist: pandas
Requires-Dist: gembox
Requires-Dist: aiohttp
Requires-Dist: pymongo
Requires-Dist: yfinance
Requires-Dist: requests
Requires-Dist: yfinance
Requires-Dist: requests
Requires-Dist: pydantic
Requires-Dist: selenium
Requires-Dist: cssselect
Requires-Dist: matplotlib
Requires-Dist: tardis_dev
Requires-Dist: transformers
Requires-Dist: nest_asyncio
Requires-Dist: python-dotenv
Requires-Dist: python-dotenv
Requires-Dist: beautifulsoup4
Requires-Dist: huggingface_hub
Requires-Dist: s3fs
Requires-Dist: numba
Requires-Dist: black
Requires-Dist: nbdev
Requires-Dist: torch
Requires-Dist: polars
Requires-Dist: fsspec
Requires-Dist: optuna
Requires-Dist: pyarrow
Requires-Dist: hyperopt
Requires-Dist: gitpython
Requires-Dist: coreforecast
Requires-Dist: utilsforecast
Requires-Dist: pytorch-lightning
